python_wrap_gcp/__init__.py
python_wrap_gcp/io.py
python_wrap_gcp/manage_instance.py
python_wrap_gcp/reload_data.py
python_wrap_gcp/configure_gcp/__init__.py
python_wrap_gcp/configure_gcp/configure.py
python_wrap_gcp/configure_gcp/gcp_template.sh
python_wrap_gcp/configure_gcp/startup_script.sh
python_wrap_gcp/docs/__init__.py
python_wrap_gcp/docs/config.py
python_wrap_gcp/misc/__init__.py
python_wrap_gcp/misc/helpers.py
python_wrap_gcp-0.0.12.dist-info/METADATA
python_wrap_gcp-0.0.12.dist-info/WHEEL
python_wrap_gcp-0.0.12.dist-info/top_level.txt
python_wrap_gcp-0.0.12.dist-info/RECORD
