Metadata-Version: 2.1
Name: python-wrap-gcp
Version: 0.0.12
Summary: Python helpers to interact with GCP
Home-page: https://github.com/vskritsk/python-wrap-gcp
Author: vskritsk
Author-email: tech@adalytica.io
License: UNKNOWN
Project-URL: Bug Tracker, https://github.com/vskritsk/python-wrap-gcp/issues
Platform: UNKNOWN
Classifier: Programming Language :: Python :: 3
Classifier: Operating System :: OS Independent
Requires-Dist: pandas (>=1.2.2)
Requires-Dist: google-cloud-storage (>=1.32.0)
Requires-Dist: fsspec (>=0.8.4)
Requires-Dist: gcsfs (>=0.7.1)
Requires-Dist: six (>=1.13.0)
Requires-Dist: python-memcached (>=1.59)
